linkreaper.py
linkreaper-0.0.6.dist-info/LICENSE
linkreaper-0.0.6.dist-info/METADATA
linkreaper-0.0.6.dist-info/WHEEL
linkreaper-0.0.6.dist-info/entry_points.txt
linkreaper-0.0.6.dist-info/top_level.txt
linkreaper-0.0.6.dist-info/RECORD
