Metadata-Version: 2.1
Name: linkreaper
Version: 0.0.6
Summary: checks for deadlinks in an html file or from a website. Done as part of DPS 909- Seneca College
Home-page: https://github.com/rubyAnneB/linkReaper-cli
Author: rubyAnneB
Author-email: bautisruby643@gmail.com
License: UNKNOWN
Platform: UNKNOWN
Classifier: Programming Language :: Python :: 3
Classifier: License :: OSI Approved :: GNU General Public License v3 (GPLv3)
Classifier: Operating System :: OS Independent
Requires-Python: >=3.6
Requires-Dist: Click
Requires-Dist: Colorama
Requires-Dist: urllib3
Requires-Dist: certifi
